README.rst
setup.py
v7/__init__.py
v7/base.py
v7/config.py
v7/core.py
v7/db_work.py
v7/dba.py
v7/dds_parser.py
v7/md_reader.py
v7/md_reader2.py
v7/metadata.py
v7/query_translator.py
v7/smb.py
v7/utils.py
v7/db/__init__.py
v7/db/alchemy.py
v7/db/db_core.py
v7/db/dbf.py
v7/db/mssql.py
v7py.egg-info/PKG-INFO
v7py.egg-info/SOURCES.txt
v7py.egg-info/dependency_links.txt
v7py.egg-info/pbr.json
v7py.egg-info/requires.txt
v7py.egg-info/top_level.txt