Metadata-Version: 1.1
Name: v7py
Version: 0.7
Summary: 1C:Enterprice v7.7 MD reader and SQL parser
Home-page: https://github.com/WorldException/v7py
Author: Stoyanov Evgeny
Author-email: quick.es@gmail.com
License: GPL
Keywords: 1C 1C:Enterprise 7.7 MD
Platform: UNKNOWN
Classifier: Development Status :: 3 - Alpha
Classifier: Intended Audience :: Developers
Classifier: Natural Language :: Russian
Classifier: License :: OSI Approved :: MIT License
Classifier: Programming Language :: Python :: 2.7
Classifier: Topic :: Software Development
Classifier: Topic :: Database
Requires: olefile
Requires: pyodbc
Requires: PySmbClient
